odoo8_addon_account_invoice_supplier_number_info-8.0.1.0.0-py2.7-nspkg.pth
odoo_addons/account_invoice_supplier_number_info/__openerp__.py
odoo_addons/account_invoice_supplier_number_info/__init__.py
odoo_addons/account_invoice_supplier_number_info/README.rst
odoo_addons/account_invoice_supplier_number_info/view/invoice_view.xml
odoo_addons/account_invoice_supplier_number_info/i18n/it.po
odoo8_addon_account_invoice_supplier_number_info-8.0.1.0.0.dist-info/top_level.txt
odoo8_addon_account_invoice_supplier_number_info-8.0.1.0.0.dist-info/WHEEL
odoo8_addon_account_invoice_supplier_number_info-8.0.1.0.0.dist-info/RECORD
odoo8_addon_account_invoice_supplier_number_info-8.0.1.0.0.dist-info/metadata.json
odoo8_addon_account_invoice_supplier_number_info-8.0.1.0.0.dist-info/DESCRIPTION.rst
odoo8_addon_account_invoice_supplier_number_info-8.0.1.0.0.dist-info/METADATA
odoo8_addon_account_invoice_supplier_number_info-8.0.1.0.0.dist-info/namespace_packages.txt
